camillademo/__init__.py
camillademo/main.py
camillademo/test_camillademo.py
camillademo-0.0.1.dist-info/LICENSE
camillademo-0.0.1.dist-info/METADATA
camillademo-0.0.1.dist-info/WHEEL
camillademo-0.0.1.dist-info/top_level.txt
camillademo-0.0.1.dist-info/RECORD
